README.md
setup.py
stratx/__init__.py
stratx/cy_partdep.c
stratx/featimp.py
stratx/ice.py
stratx/partdep.py
stratx/plot.py
stratx.egg-info/PKG-INFO
stratx.egg-info/SOURCES.txt
stratx.egg-info/dependency_links.txt
stratx.egg-info/requires.txt
stratx.egg-info/top_level.txt