Metadata-Version: 1.2
Name: stratx
Version: 0.5
Summary: Model-independent partial dependence plots in Python 3 that works even for codependent variables
Home-page: https://github.com/parrt/stratx
Author: Terence Parr
Author-email: parrt@antlr.org
License: MIT
Keywords: model-independent net-effect plots,visualization,partial dependence plots,partial derivative plots,ICE plots,feature importance
Platform: UNKNOWN
Classifier: License :: OSI Approved :: MIT License
Classifier: Intended Audience :: Developers
Requires-Python: >=3.6
